predictionguard/__init__.py
predictionguard/client.py
predictionguard/version.py
predictionguard/src/audio.py
predictionguard/src/chat.py
predictionguard/src/completions.py
predictionguard/src/detokenize.py
predictionguard/src/documents.py
predictionguard/src/embeddings.py
predictionguard/src/factuality.py
predictionguard/src/injection.py
predictionguard/src/models.py
predictionguard/src/pii.py
predictionguard/src/rerank.py
predictionguard/src/tokenize.py
predictionguard/src/toxicity.py
predictionguard/src/translate.py
predictionguard-2.9.2.dist-info/licenses/LICENSE
predictionguard-2.9.2.dist-info/WHEEL
predictionguard-2.9.2.dist-info/METADATA
predictionguard-2.9.2.dist-info/RECORD
